{
  "ts": [
    [
      [
        "ReadVariableFromFile",
        {
          "var_name": "ts",
          "need_time_bounds": false
        }
      ],
      [
        "CorrectTime",
        {
          "offset": {
            "SRF": 0
          }
        }
      ],
      [
        "SaveVariableToDisk",
        {
          "new_attributes": {
            "long_name": "Surface Temperature",
            "standard_name": "surface_temperature",
            "units": "K"
          }
        }
      ],
      [
        "ComputeAverage",
        {
          "new_time_step": 24
        }
      ],
      [
        "SaveVariableToDisk",
        {
          "new_attributes": {
            "long_name": "Surface Temperature",
            "standard_name": "surface_temperature",
            "units": "K"
          }
        }
      ]
    ]
  ]
}

